ghog/__init__.py
ghog/checks.py
ghog/constants.py
ghog/filt.py
ghog/h5io.py
ghog/merge_csrs.py
ghog/nmo.py
ghog/restack.py
ghog/stolt.py
ghog-0.0.1.dist-info/METADATA
ghog-0.0.1.dist-info/WHEEL
ghog-0.0.1.dist-info/entry_points.txt
ghog-0.0.1.dist-info/top_level.txt
ghog-0.0.1.dist-info/RECORD
